app/__init__.py
app/subsys.py
commands/__init__.py
commands/config.py
commands/init.py
commands/snap.py
commands/submit.py
services/__init__.py
services/auth.py
services/submit.py
utils/__init__.py
utils/misc.py
utils/repository.py
utils/snap.py
utils/stage.py
amalitech_subsys_june-0.9.11.dist-info/LICENSE
amalitech_subsys_june-0.9.11.dist-info/METADATA
amalitech_subsys_june-0.9.11.dist-info/WHEEL
amalitech_subsys_june-0.9.11.dist-info/entry_points.txt
amalitech_subsys_june-0.9.11.dist-info/top_level.txt
amalitech_subsys_june-0.9.11.dist-info/RECORD
